MANIFEST.in
README.md
setup.py
admin_exporter/__init__.py
admin_exporter/actions.py
admin_exporter/models.py
admin_exporter/tests.py
admin_exporter/utils.py
admin_exporter/views.py
django_admin_exporter.egg-info/PKG-INFO
django_admin_exporter.egg-info/SOURCES.txt
django_admin_exporter.egg-info/dependency_links.txt
django_admin_exporter.egg-info/not-zip-safe
django_admin_exporter.egg-info/requires.txt
django_admin_exporter.egg-info/top_level.txt