Metadata-Version: 1.0
Name: django-admin-exporter
Version: 0.2.1
Summary: Simple admin actions to download/export selected items in CSV, JSON, XML, etc.
Home-page: https://github.com/RyanBalfanz/django-admin-exporter
Author: Ryan Balfanz
Author-email: ryan@ryanbalfanz.net
License: UNKNOWN
Platform: any
Classifier: Environment :: Web Environment
Classifier: Intended Audience :: Developers
Classifier: Operating System :: OS Independent
Classifier: Programming Language :: Python
Classifier: Topic :: Internet :: WWW/HTTP :: Dynamic Content
Classifier: Topic :: Software Development :: Libraries :: Python Modules
